jaad/__init__.py
jaad/backends.py
jaad/exceptions.py
jaad/permissions.py
jaad/renderers.py
jaad/routes.py
jaad/utils.py
jaad/view.py
jaad/forms/__init__.py
jaad/forms/fields.py
jaad/forms/groups.py
jaad/forms/tests/__init__.py
jaad/forms/tests/test_fields.py
jaad/forms/tests/test_groups.py
jaad/templates/add-uwsgi/webapp.ini
jaad/templates/add-uwsgi/server/uwsgi.py
jaad/templates/startproject/manage.py
jaad/templates/startproject/server/__init__.py
jaad/templates/startproject/server/urls.py
jaad/templates/startproject/server/apps/__init__.py
jaad/templates/startproject/server/apps/documentation/__init__.py
jaad/templates/startproject/server/apps/documentation/urls.py
jaad/templates/startproject/server/apps/documentation/static/css/documentation.css
jaad/templates/startproject/server/apps/documentation/templates/rest_framework_swagger/base.html
jaad/templates/startproject/server/apps/documentation/templates/rest_framework_swagger/index.html
jaad/templates/startproject/server/apps/index/__init__.py
jaad/templates/startproject/server/apps/index/parameters.py
jaad/templates/startproject/server/apps/index/view.py
jaad/templates/startproject/server/settings/__init__.py
jaad/templates/startproject/server/settings/application.py
jaad/templates/startproject/server/settings/local.py
jaad/tests/__init__.py
jaad/tests/settings.py
jaad/tests/test_backends.py
jaad/tests/test_exceptions.py
jaad/tests/test_renderers.py
jaad/tests/test_view.py
jaad-0.11.data/scripts/jaad-admin.py
jaad-0.11.dist-info/LICENSE
jaad-0.11.dist-info/METADATA
jaad-0.11.dist-info/WHEEL
jaad-0.11.dist-info/top_level.txt
jaad-0.11.dist-info/RECORD
