Metadata-Version: 2.1
Name: jaad
Version: 0.11
Summary: An additional layer to Django aiming to simplify resilient API creation
Home-page: https://github.com/AmadeusITGroup/Jaad
Author: Erwan Guyomarc'h
Author-email: erwan.guyomarch@amadeus.com
License: UNKNOWN
Platform: UNKNOWN
Classifier: Development Status :: 5 - Production/Stable
Classifier: Programming Language :: Python :: 3
Classifier: Programming Language :: Python :: 3 :: Only
Classifier: Programming Language :: Python :: Implementation :: CPython
Classifier: Programming Language :: Python :: Implementation :: PyPy
Requires-Python: >=3.6.1
License-File: LICENSE
Requires-Dist: django (~=3.1.0)
Requires-Dist: djangorestframework-csv (~=2.1.0)
Requires-Dist: django-rest-swagger (~=2.2.0)
Requires-Dist: django-filter (~=2.4.0)
Requires-Dist: djangorestframework (~=3.12.0)
Requires-Dist: django-crispy-forms (~=1.11.0)
Requires-Dist: django-cors-headers (~=3.7.0)
Provides-Extra: local
Requires-Dist: tox (~=3.22.0) ; extra == 'local'
